{
  "identity": {
    "bid": "353899681110jid85865774756093lid",
    "phone": "+353899681110",
    "jid": "353899681110@s.whatsapp.net",
    "lid": "85865774756093@lid",
    "cleanJid": "353899681110",
    "cleanLid": "85865774756093"
  },
  "status": {
    "dsgvo": {
      "accepted": false,
      "rejected": false,
      "acceptedAt": null
    },
    "verified": false,
    "unverify": true,
    "mappedAt": "2026-07-09T16:36:06.232Z",
    "registeredAt": null
  },
  "progression": {
    "level": 0,
    "prestige": 0,
    "xp": 0,
    "neededXpForLvOrPrestigeUp": 743
  },
  "casino": {
    "gamesPlayed": 0,
    "lastWin": 0,
    "totalWin": 0,
    "highestWin": 0,
    "winStreak": 0,
    "highestWinStreak": 0,
    "lastLoss": 0,
    "totalLoss": 0,
    "highestLoss": 0,
    "lossStreak": 0,
    "highestLossStreak": 0
  },
  "wallet": {
    "copper": 0,
    "silver": 0,
    "gold": 0,
    "platin": 0
  },
  "bank": {
    "active": false,
    "copper": 0,
    "silver": 0,
    "gold": 0,
    "platin": 0
  },
  "rewards": {
    "lastDaily": null,
    "lastWeekly": null,
    "lastMonthly": null,
    "lastYearly": null
  }
}